aiosnow/__init__.py
aiosnow/client.py
aiosnow/config.py
aiosnow/consts.py
aiosnow/exceptions.py
aiosnow/models/__init__.py
aiosnow/models/_base/__init__.py
aiosnow/models/_base/model.py
aiosnow/models/_base/table.py
aiosnow/models/_schema/__init__.py
aiosnow/models/_schema/fields/__init__.py
aiosnow/models/_schema/fields/base.py
aiosnow/models/_schema/fields/boolean.py
aiosnow/models/_schema/fields/datetime.py
aiosnow/models/_schema/fields/integer.py
aiosnow/models/_schema/fields/mapped.py
aiosnow/models/_schema/fields/string.py
aiosnow/models/_schema/helpers/__init__.py
aiosnow/models/_schema/helpers/pluck.py
aiosnow/models/_schema/nested.py
aiosnow/models/_schema/schema.py
aiosnow/models/attachment/__init__.py
aiosnow/models/attachment/file.py
aiosnow/models/attachment/model.py
aiosnow/models/attachment/schema.py
aiosnow/models/table/__init__.py
aiosnow/models/table/declared/__init__.py
aiosnow/models/table/declared/incident.py
aiosnow/models/table/declared/journal.py
aiosnow/models/table/model.py
aiosnow/query/__init__.py
aiosnow/query/condition.py
aiosnow/query/fields/__init__.py
aiosnow/query/fields/base.py
aiosnow/query/fields/boolean.py
aiosnow/query/fields/datetime.py
aiosnow/query/fields/integer.py
aiosnow/query/fields/string.py
aiosnow/query/fields/utils.py
aiosnow/query/operators.py
aiosnow/query/selector.py
aiosnow/query/utils.py
aiosnow/request/__init__.py
aiosnow/request/base.py
aiosnow/request/delete.py
aiosnow/request/get.py
aiosnow/request/helpers/__init__.py
aiosnow/request/helpers/pagestream.py
aiosnow/request/methods.py
aiosnow/request/patch.py
aiosnow/request/post.py
aiosnow/request/response/__init__.py
aiosnow/request/response/schemas.py
aiosnow/utils.py
aiosnow-0.6.0.dist-info/LICENSE
aiosnow-0.6.0.dist-info/WHEEL
aiosnow-0.6.0.dist-info/METADATA
aiosnow-0.6.0.dist-info/RECORD
